Metadata-Version: 2.1
Name: dependency-injector-fg
Version: 4.44.2
Summary: Dependency injection framework for Python - FORK by gortibaldik
Author-email: Roman Mogylatov <rmogilatov@gmail.com>
Maintainer-email: František Trebuňa <ferotre@gmail.com>
License: Copyright (c) 2024, Roman Mogylatov
Project-URL: Homepage, https://github.com/gortibaldik/python-dependency-injector
Project-URL: Documentation, https://python-dependency-injector.ets-labs.org/
Project-URL: Download, https://pypi.python.org/pypi/dependency_injector-fg
Keywords: Dependency injection,DI,Inversion of Control,IoC,Factory,Singleton,Design patterns,Flask
Classifier: Development Status :: 5 - Production/Stable
Classifier: Intended Audience :: Developers
Classifier: License :: OSI Approved :: BSD License
Classifier: Operating System :: OS Independent
Classifier: Programming Language :: Python :: 3.10
Classifier: Programming Language :: Python :: Implementation :: CPython
Classifier: Framework :: AsyncIO
Classifier: Framework :: Bottle
Classifier: Framework :: Django
Classifier: Framework :: Flask
Classifier: Framework :: Pylons
Classifier: Framework :: Pyramid
Classifier: Framework :: Pytest
Classifier: Framework :: TurboGears
Classifier: Topic :: Software Development
Classifier: Topic :: Software Development :: Libraries
Classifier: Topic :: Software Development :: Libraries :: Python Modules
Requires-Python: >=3.7
License-File: LICENSE.rst
Requires-Dist: six
Provides-Extra: yaml
Requires-Dist: pyyaml; extra == "yaml"
Provides-Extra: pydantic
Requires-Dist: pydantic; extra == "pydantic"
Provides-Extra: pydantic2
Requires-Dist: pydantic-settings; extra == "pydantic2"
Provides-Extra: flask
Requires-Dist: flask; extra == "flask"
Provides-Extra: aiohttp
Requires-Dist: aiohttp; extra == "aiohttp"
